eco_code_analyzer/__init__.py
eco_code_analyzer/analyzer.py
eco_code_analyzer/cli.py
eco_code_analyzer/rules.py
eco_code_analyzer/rules/__init__.py
eco_code_analyzer/rules/algorithm.py
eco_code_analyzer/rules/base.py
eco_code_analyzer/rules/context.py
eco_code_analyzer/rules/energy.py
eco_code_analyzer/rules/io.py
eco_code_analyzer/rules/memory.py
eco_code_analyzer/rules/patterns.py
eco_code_analyzer-0.4.0.dist-info/METADATA
eco_code_analyzer-0.4.0.dist-info/WHEEL
eco_code_analyzer-0.4.0.dist-info/entry_points.txt
eco_code_analyzer-0.4.0.dist-info/top_level.txt
eco_code_analyzer-0.4.0.dist-info/RECORD
