Metadata-Version: 2.2
Name: eco-code-analyzer
Version: 0.4.0
Summary: A Python library that analyzes code for ecological impact and provides optimization suggestions with enhanced rule system
Home-page: https://github.com/vinerya/eco-code-analyzer
Author: Moudather Chelbi
Author-email: moudather.chelbi@gmail.com
Keywords: code analysis,environmental impact,energy efficiency,eco-friendly coding,static analysis,green computing
Classifier: Programming Language :: Python :: 3
Classifier: License :: OSI Approved :: MIT License
Classifier: Operating System :: OS Independent
Classifier: Intended Audience :: Developers
Classifier: Topic :: Software Development :: Quality Assurance
Classifier: Topic :: Software Development :: Testing
Classifier: Topic :: Software Development :: Libraries :: Python Modules
Requires-Python: >=3.7
Requires-Dist: astroid
Requires-Dist: gitpython
Requires-Dist: matplotlib
Requires-Dist: typing_extensions; python_version < "3.8"
Provides-Extra: dev
Requires-Dist: pytest; extra == "dev"
Requires-Dist: flake8; extra == "dev"
Requires-Dist: black; extra == "dev"
Requires-Dist: mypy; extra == "dev"
Requires-Dist: coverage; extra == "dev"
Dynamic: author
Dynamic: author-email
Dynamic: classifier
Dynamic: description
Dynamic: description-content-type
Dynamic: home-page
Dynamic: keywords
Dynamic: provides-extra
Dynamic: requires-dist
Dynamic: requires-python
Dynamic: summary
